EasyStatistics/Binomialdistribution.py
EasyStatistics/Gaussiandistribution.py
EasyStatistics/Generaldistribution.py
EasyStatistics/__init__.py
EasyStatistics-0.4.dist-info/DESCRIPTION.rst
EasyStatistics-0.4.dist-info/METADATA
EasyStatistics-0.4.dist-info/RECORD
EasyStatistics-0.4.dist-info/WHEEL
EasyStatistics-0.4.dist-info/metadata.json
EasyStatistics-0.4.dist-info/top_level.txt
