Metadata-Version: 2.0
Name: EasyStatistics
Version: 0.4
Summary: Making Gaussian and Binomial distributions easy to work with.
Home-page: UNKNOWN
Author: UNKNOWN
Author-email: sapra.ritvik@outlook.com
License: UNKNOWN
Platform: UNKNOWN
